pyscript_util/__init__.py
pyscript_util/config_example.py
pyscript_util/config_manager.py
pyscript_util/pyscript_util.py
pyscript_util-0.1.12.dist-info/METADATA
pyscript_util-0.1.12.dist-info/WHEEL
pyscript_util-0.1.12.dist-info/entry_points.txt
pyscript_util-0.1.12.dist-info/top_level.txt
pyscript_util-0.1.12.dist-info/RECORD
